ridesystems/__init__.py
ridesystems/api.py
ridesystems/py.typed
ridesystems/reports.py
ridesystems-2.0.9.dist-info/AUTHORS.rst
ridesystems-2.0.9.dist-info/LICENSE.txt
ridesystems-2.0.9.dist-info/METADATA
ridesystems-2.0.9.dist-info/WHEEL
ridesystems-2.0.9.dist-info/top_level.txt
ridesystems-2.0.9.dist-info/RECORD
