Metadata-Version: 2.1
Name: ridesystems
Version: 2.0.9
Summary: Add a short description here!
Home-page: https://github.com/city-of-baltimore/ridesystems
Author: Brian Seel
Author-email: Brian.Seel@baltimorecity.gov
License: MIT
Project-URL: Source, https://github.com/city-of-baltimore/ridesystems
Project-URL: Download, https://pypi.org/project/ridesystems/#files
Project-URL: Twitter, https://twitter.com/cylussec
Platform: any
Classifier: Development Status :: 5 - Production/Stable
Classifier: Programming Language :: Python
License-File: LICENSE.txt
License-File: AUTHORS.rst
Requires-Dist: pandas
Requires-Dist: mechanize
Requires-Dist: requests
Requires-Dist: beautifulsoup4
Requires-Dist: tenacity
Requires-Dist: loguru
Requires-Dist: importlib-metadata ; python_version < "3.8"
Provides-Extra: testing
Requires-Dist: setuptools ; extra == 'testing'
Requires-Dist: pytest ; extra == 'testing'
Requires-Dist: pytest-cov ; extra == 'testing'
